cognito_local/__init__.py
cognito_local/main.py
cognito_local/patch.py
cognito_local/storage.py
cognito_local-0.1.0.dist-info/METADATA
cognito_local-0.1.0.dist-info/WHEEL
cognito_local-0.1.0.dist-info/entry_points.txt
cognito_local-0.1.0.dist-info/licenses/LICENSE
cognito_local-0.1.0.dist-info/RECORD
