Metadata-Version: 2.4
Name: cognito-local
Version: 0.1.0
Summary: A lightweight, persistent Cognito mock server using Moto with file-based state persistence.
Project-URL: Homepage, https://github.com/m-ali-ubit/cognito-local
Project-URL: Repository, https://github.com/m-ali-ubit/cognito-local
Project-URL: Issues, https://github.com/m-ali-ubit/cognito-local/issues
Author-email: Muhammad Ali <usermalikhan@gmail.com>
License: Apache-2.0
License-File: LICENSE
Keywords: aws,cognito,cognito-idp,local,mock,moto,serverless
Classifier: Intended Audience :: Developers
Classifier: Operating System :: OS Independent
Classifier: Programming Language :: Python :: 3
Classifier: Programming Language :: Python :: 3.9
Classifier: Programming Language :: Python :: 3.10
Classifier: Programming Language :: Python :: 3.11
Classifier: Programming Language :: Python :: 3.12
Classifier: Programming Language :: Python :: 3.13
Classifier: Topic :: Software Development :: Testing :: Mocking
Requires-Python: >=3.9
Requires-Dist: cryptography
Requires-Dist: flask
Requires-Dist: moto[cognitoidentity,cognitoidp,server]>=5.0.0
Requires-Dist: werkzeug
Provides-Extra: dev
Requires-Dist: build; extra == 'dev'
Requires-Dist: pre-commit; extra == 'dev'
Requires-Dist: pytest; extra == 'dev'
Requires-Dist: ruff; extra == 'dev'
Requires-Dist: twine; extra == 'dev'
